{
  "lessons": [
    {
      "academy": "rw",
      "unit": "Reading Skills",
      "lesson_id": "words-in-context",
      "title": "Words in Context",
      "route": "/sat-rw-academy/lesson/words-in-context",
      "has_objective": true,
      "has_teaching": true,
      "has_worked_examples": true,
      "has_common_mistakes": true,
      "has_strategy": true,
      "has_knowledge_check": true,
      "has_practice": true,
      "has_mastery_score": true,
      "has_recommendation": true,
      "is_placeholder": false,
      "raw_markdown_risk": false,
      "broken_equation_risk": false,
      "duplicate_example_risk": false,
      "premium_gated": true,
      "action": "retain"
    },
    {
      "academy": "rw",
      "unit": "Reading Skills",
      "lesson_id": "central-ideas-details",
      "title": "Central Ideas & Details",
      "route": "/sat-rw-academy/lesson/central-ideas-details",
      "has_objective": true,
      "has_teaching": true,
      "has_worked_examples": true,
      "has_common_mistakes": true,
      "has_strategy": true,
      "has_knowledge_check": true,
      "has_practice": true,
      "has_mastery_score": true,
      "has_recommendation": true,
      "is_placeholder": false,
      "raw_markdown_risk": false,
      "broken_equation_risk": false,
      "duplicate_example_risk": false,
      "premium_gated": true,
      "action": "retain"
    },
    {
      "academy": "rw",
      "unit": "Reading Skills",
      "lesson_id": "text-structure-purpose",
      "title": "Text Structure & Purpose",
      "route": "/sat-rw-academy/lesson/text-structure-purpose",
      "has_objective": true,
      "has_teaching": true,
      "has_worked_examples": true,
      "has_common_mistakes": true,
      "has_strategy": true,
      "has_knowledge_check": true,
      "has_practice": true,
      "has_mastery_score": true,
      "has_recommendation": true,
      "is_placeholder": false,
      "raw_markdown_risk": false,
      "broken_equation_risk": false,
      "duplicate_example_risk": false,
      "premium_gated": true,
      "action": "retain"
    },
    {
      "academy": "rw",
      "unit": "Reading Skills",
      "lesson_id": "command-of-evidence",
      "title": "Command of Evidence",
      "route": "/sat-rw-academy/lesson/command-of-evidence",
      "has_objective": true,
      "has_teaching": true,
      "has_worked_examples": true,
      "has_common_mistakes": true,
      "has_strategy": true,
      "has_knowledge_check": true,
      "has_practice": true,
      "has_mastery_score": true,
      "has_recommendation": true,
      "is_placeholder": false,
      "raw_markdown_risk": false,
      "broken_equation_risk": false,
      "duplicate_example_risk": false,
      "premium_gated": true,
      "action": "retain"
    },
    {
      "academy": "rw",
      "unit": "Reading Skills",
      "lesson_id": "quantitative-evidence",
      "title": "Quantitative Evidence",
      "route": "/sat-rw-academy/lesson/quantitative-evidence",
      "has_objective": true,
      "has_teaching": true,
      "has_worked_examples": true,
      "has_common_mistakes": true,
      "has_strategy": true,
      "has_knowledge_check": true,
      "has_practice": true,
      "has_mastery_score": true,
      "has_recommendation": true,
      "is_placeholder": false,
      "raw_markdown_risk": false,
      "broken_equation_risk": false,
      "duplicate_example_risk": false,
      "premium_gated": true,
      "action": "retain"
    },
    {
      "academy": "rw",
      "unit": "Reading Skills",
      "lesson_id": "inferences",
      "title": "Inferences",
      "route": "/sat-rw-academy/lesson/inferences",
      "has_objective": true,
      "has_teaching": true,
      "has_worked_examples": true,
      "has_common_mistakes": true,
      "has_strategy": true,
      "has_knowledge_check": true,
      "has_practice": true,
      "has_mastery_score": true,
      "has_recommendation": true,
      "is_placeholder": false,
      "raw_markdown_risk": false,
      "broken_equation_risk": false,
      "duplicate_example_risk": false,
      "premium_gated": true,
      "action": "retain"
    },
    {
      "academy": "rw",
      "unit": "Reading Skills",
      "lesson_id": "cross-text-connections",
      "title": "Cross-Text Connections",
      "route": "/sat-rw-academy/lesson/cross-text-connections",
      "has_objective": true,
      "has_teaching": true,
      "has_worked_examples": true,
      "has_common_mistakes": true,
      "has_strategy": true,
      "has_knowledge_check": true,
      "has_practice": true,
      "has_mastery_score": true,
      "has_recommendation": true,
      "is_placeholder": false,
      "raw_markdown_risk": false,
      "broken_equation_risk": false,
      "duplicate_example_risk": false,
      "premium_gated": true,
      "action": "retain"
    },
    {
      "academy": "rw",
      "unit": "Writing Skills",
      "lesson_id": "boundaries",
      "title": "Boundaries",
      "route": "/sat-rw-academy/lesson/boundaries",
      "has_objective": true,
      "has_teaching": true,
      "has_worked_examples": true,
      "has_common_mistakes": true,
      "has_strategy": true,
      "has_knowledge_check": true,
      "has_practice": true,
      "has_mastery_score": true,
      "has_recommendation": true,
      "is_placeholder": false,
      "raw_markdown_risk": false,
      "broken_equation_risk": false,
      "duplicate_example_risk": false,
      "premium_gated": true,
      "action": "retain"
    },
    {
      "academy": "rw",
      "unit": "Writing Skills",
      "lesson_id": "form-structure-sense",
      "title": "Form, Structure & Sense",
      "route": "/sat-rw-academy/lesson/form-structure-sense",
      "has_objective": true,
      "has_teaching": true,
      "has_worked_examples": true,
      "has_common_mistakes": true,
      "has_strategy": true,
      "has_knowledge_check": true,
      "has_practice": true,
      "has_mastery_score": true,
      "has_recommendation": true,
      "is_placeholder": false,
      "raw_markdown_risk": false,
      "broken_equation_risk": false,
      "duplicate_example_risk": false,
      "premium_gated": true,
      "action": "retain"
    },
    {
      "academy": "rw",
      "unit": "Writing Skills",
      "lesson_id": "transitions",
      "title": "Transitions",
      "route": "/sat-rw-academy/lesson/transitions",
      "has_objective": true,
      "has_teaching": true,
      "has_worked_examples": true,
      "has_common_mistakes": true,
      "has_strategy": true,
      "has_knowledge_check": true,
      "has_practice": true,
      "has_mastery_score": true,
      "has_recommendation": true,
      "is_placeholder": false,
      "raw_markdown_risk": false,
      "broken_equation_risk": false,
      "duplicate_example_risk": false,
      "premium_gated": true,
      "action": "retain"
    },
    {
      "academy": "rw",
      "unit": "Writing Skills",
      "lesson_id": "rhetorical-synthesis",
      "title": "Rhetorical Synthesis",
      "route": "/sat-rw-academy/lesson/rhetorical-synthesis",
      "has_objective": true,
      "has_teaching": true,
      "has_worked_examples": true,
      "has_common_mistakes": true,
      "has_strategy": true,
      "has_knowledge_check": true,
      "has_practice": true,
      "has_mastery_score": true,
      "has_recommendation": true,
      "is_placeholder": false,
      "raw_markdown_risk": false,
      "broken_equation_risk": false,
      "duplicate_example_risk": false,
      "premium_gated": true,
      "action": "retain"
    },
    {
      "academy": "math",
      "unit": "Algebra",
      "lesson_id": "linear-equations",
      "title": "Linear Equations",
      "route": "/sat-math-academy/lesson/linear-equations",
      "has_objective": true,
      "has_teaching": true,
      "has_worked_examples": true,
      "has_common_mistakes": true,
      "has_strategy": true,
      "has_knowledge_check": true,
      "has_practice": true,
      "has_mastery_score": true,
      "has_recommendation": true,
      "is_placeholder": false,
      "raw_markdown_risk": false,
      "broken_equation_risk": false,
      "duplicate_example_risk": false,
      "premium_gated": true,
      "action": "retain"
    },
    {
      "academy": "math",
      "unit": "Algebra",
      "lesson_id": "linear-equations-two-variables",
      "title": "Linear Equations Two Variables",
      "route": "/sat-math-academy/lesson/linear-equations-two-variables",
      "has_objective": true,
      "has_teaching": true,
      "has_worked_examples": true,
      "has_common_mistakes": true,
      "has_strategy": true,
      "has_knowledge_check": true,
      "has_practice": true,
      "has_mastery_score": true,
      "has_recommendation": true,
      "is_placeholder": false,
      "raw_markdown_risk": false,
      "broken_equation_risk": false,
      "duplicate_example_risk": false,
      "premium_gated": true,
      "action": "retain"
    },
    {
      "academy": "math",
      "unit": "Algebra",
      "lesson_id": "linear-functions",
      "title": "Linear Functions",
      "route": "/sat-math-academy/lesson/linear-functions",
      "has_objective": true,
      "has_teaching": true,
      "has_worked_examples": true,
      "has_common_mistakes": true,
      "has_strategy": true,
      "has_knowledge_check": true,
      "has_practice": true,
      "has_mastery_score": true,
      "has_recommendation": true,
      "is_placeholder": false,
      "raw_markdown_risk": false,
      "broken_equation_risk": false,
      "duplicate_example_risk": false,
      "premium_gated": true,
      "action": "retain"
    },
    {
      "academy": "math",
      "unit": "Algebra",
      "lesson_id": "systems-of-equations",
      "title": "Systems Of Equations",
      "route": "/sat-math-academy/lesson/systems-of-equations",
      "has_objective": true,
      "has_teaching": true,
      "has_worked_examples": true,
      "has_common_mistakes": true,
      "has_strategy": true,
      "has_knowledge_check": true,
      "has_practice": true,
      "has_mastery_score": true,
      "has_recommendation": true,
      "is_placeholder": false,
      "raw_markdown_risk": false,
      "broken_equation_risk": false,
      "duplicate_example_risk": false,
      "premium_gated": true,
      "action": "retain"
    },
    {
      "academy": "math",
      "unit": "Algebra",
      "lesson_id": "linear-inequalities",
      "title": "Linear Inequalities",
      "route": "/sat-math-academy/lesson/linear-inequalities",
      "has_objective": true,
      "has_teaching": true,
      "has_worked_examples": true,
      "has_common_mistakes": true,
      "has_strategy": true,
      "has_knowledge_check": true,
      "has_practice": true,
      "has_mastery_score": true,
      "has_recommendation": true,
      "is_placeholder": false,
      "raw_markdown_risk": false,
      "broken_equation_risk": false,
      "duplicate_example_risk": false,
      "premium_gated": true,
      "action": "retain"
    },
    {
      "academy": "math",
      "unit": "Advanced Math",
      "lesson_id": "equivalent-expressions",
      "title": "Equivalent Expressions",
      "route": "/sat-math-academy/lesson/equivalent-expressions",
      "has_objective": true,
      "has_teaching": true,
      "has_worked_examples": true,
      "has_common_mistakes": true,
      "has_strategy": true,
      "has_knowledge_check": true,
      "has_practice": true,
      "has_mastery_score": true,
      "has_recommendation": true,
      "is_placeholder": false,
      "raw_markdown_risk": false,
      "broken_equation_risk": false,
      "duplicate_example_risk": false,
      "premium_gated": true,
      "action": "retain"
    },
    {
      "academy": "math",
      "unit": "Advanced Math",
      "lesson_id": "quadratic-equations",
      "title": "Quadratic Equations",
      "route": "/sat-math-academy/lesson/quadratic-equations",
      "has_objective": true,
      "has_teaching": true,
      "has_worked_examples": true,
      "has_common_mistakes": true,
      "has_strategy": true,
      "has_knowledge_check": true,
      "has_practice": true,
      "has_mastery_score": true,
      "has_recommendation": true,
      "is_placeholder": false,
      "raw_markdown_risk": false,
      "broken_equation_risk": false,
      "duplicate_example_risk": false,
      "premium_gated": true,
      "action": "retain"
    },
    {
      "academy": "math",
      "unit": "Advanced Math",
      "lesson_id": "exponential-functions",
      "title": "Exponential Functions",
      "route": "/sat-math-academy/lesson/exponential-functions",
      "has_objective": true,
      "has_teaching": true,
      "has_worked_examples": true,
      "has_common_mistakes": true,
      "has_strategy": true,
      "has_knowledge_check": true,
      "has_practice": true,
      "has_mastery_score": true,
      "has_recommendation": true,
      "is_placeholder": false,
      "raw_markdown_risk": false,
      "broken_equation_risk": false,
      "duplicate_example_risk": false,
      "premium_gated": true,
      "action": "retain"
    },
    {
      "academy": "math",
      "unit": "Advanced Math",
      "lesson_id": "polynomial-expressions",
      "title": "Polynomial Expressions",
      "route": "/sat-math-academy/lesson/polynomial-expressions",
      "has_objective": true,
      "has_teaching": true,
      "has_worked_examples": true,
      "has_common_mistakes": true,
      "has_strategy": true,
      "has_knowledge_check": true,
      "has_practice": true,
      "has_mastery_score": true,
      "has_recommendation": true,
      "is_placeholder": false,
      "raw_markdown_risk": false,
      "broken_equation_risk": false,
      "duplicate_example_risk": false,
      "premium_gated": true,
      "action": "retain"
    },
    {
      "academy": "math",
      "unit": "Advanced Math",
      "lesson_id": "radical-rational-equations",
      "title": "Radical Rational Equations",
      "route": "/sat-math-academy/lesson/radical-rational-equations",
      "has_objective": true,
      "has_teaching": true,
      "has_worked_examples": true,
      "has_common_mistakes": true,
      "has_strategy": true,
      "has_knowledge_check": true,
      "has_practice": true,
      "has_mastery_score": true,
      "has_recommendation": true,
      "is_placeholder": false,
      "raw_markdown_risk": false,
      "broken_equation_risk": false,
      "duplicate_example_risk": false,
      "premium_gated": true,
      "action": "retain"
    },
    {
      "academy": "math",
      "unit": "Advanced Math",
      "lesson_id": "nonlinear-equations-systems",
      "title": "Nonlinear Equations Systems",
      "route": "/sat-math-academy/lesson/nonlinear-equations-systems",
      "has_objective": true,
      "has_teaching": true,
      "has_worked_examples": true,
      "has_common_mistakes": true,
      "has_strategy": true,
      "has_knowledge_check": true,
      "has_practice": true,
      "has_mastery_score": true,
      "has_recommendation": true,
      "is_placeholder": false,
      "raw_markdown_risk": false,
      "broken_equation_risk": false,
      "duplicate_example_risk": false,
      "premium_gated": true,
      "action": "retain"
    },
    {
      "academy": "math",
      "unit": "Problem-Solving & Data Analysis",
      "lesson_id": "ratios-rates-units",
      "title": "Ratios Rates Units",
      "route": "/sat-math-academy/lesson/ratios-rates-units",
      "has_objective": true,
      "has_teaching": true,
      "has_worked_examples": true,
      "has_common_mistakes": true,
      "has_strategy": true,
      "has_knowledge_check": true,
      "has_practice": true,
      "has_mastery_score": true,
      "has_recommendation": true,
      "is_placeholder": false,
      "raw_markdown_risk": false,
      "broken_equation_risk": false,
      "duplicate_example_risk": false,
      "premium_gated": true,
      "action": "retain"
    },
    {
      "academy": "math",
      "unit": "Problem-Solving & Data Analysis",
      "lesson_id": "percentages",
      "title": "Percentages",
      "route": "/sat-math-academy/lesson/percentages",
      "has_objective": true,
      "has_teaching": true,
      "has_worked_examples": true,
      "has_common_mistakes": true,
      "has_strategy": true,
      "has_knowledge_check": true,
      "has_practice": true,
      "has_mastery_score": true,
      "has_recommendation": true,
      "is_placeholder": false,
      "raw_markdown_risk": false,
      "broken_equation_risk": false,
      "duplicate_example_risk": false,
      "premium_gated": true,
      "action": "retain"
    },
    {
      "academy": "math",
      "unit": "Problem-Solving & Data Analysis",
      "lesson_id": "one-variable-data",
      "title": "One Variable Data",
      "route": "/sat-math-academy/lesson/one-variable-data",
      "has_objective": true,
      "has_teaching": true,
      "has_worked_examples": true,
      "has_common_mistakes": true,
      "has_strategy": true,
      "has_knowledge_check": true,
      "has_practice": true,
      "has_mastery_score": true,
      "has_recommendation": true,
      "is_placeholder": false,
      "raw_markdown_risk": false,
      "broken_equation_risk": false,
      "duplicate_example_risk": false,
      "premium_gated": true,
      "action": "retain"
    },
    {
      "academy": "math",
      "unit": "Problem-Solving & Data Analysis",
      "lesson_id": "two-variable-data",
      "title": "Two Variable Data",
      "route": "/sat-math-academy/lesson/two-variable-data",
      "has_objective": true,
      "has_teaching": true,
      "has_worked_examples": true,
      "has_common_mistakes": true,
      "has_strategy": true,
      "has_knowledge_check": true,
      "has_practice": true,
      "has_mastery_score": true,
      "has_recommendation": true,
      "is_placeholder": false,
      "raw_markdown_risk": false,
      "broken_equation_risk": false,
      "duplicate_example_risk": false,
      "premium_gated": true,
      "action": "retain"
    },
    {
      "academy": "math",
      "unit": "Problem-Solving & Data Analysis",
      "lesson_id": "probability",
      "title": "Probability",
      "route": "/sat-math-academy/lesson/probability",
      "has_objective": true,
      "has_teaching": true,
      "has_worked_examples": true,
      "has_common_mistakes": true,
      "has_strategy": true,
      "has_knowledge_check": true,
      "has_practice": true,
      "has_mastery_score": true,
      "has_recommendation": true,
      "is_placeholder": false,
      "raw_markdown_risk": false,
      "broken_equation_risk": false,
      "duplicate_example_risk": false,
      "premium_gated": true,
      "action": "retain"
    },
    {
      "academy": "math",
      "unit": "Problem-Solving & Data Analysis",
      "lesson_id": "statistical-claims",
      "title": "Statistical Claims",
      "route": "/sat-math-academy/lesson/statistical-claims",
      "has_objective": true,
      "has_teaching": true,
      "has_worked_examples": true,
      "has_common_mistakes": true,
      "has_strategy": true,
      "has_knowledge_check": true,
      "has_practice": true,
      "has_mastery_score": true,
      "has_recommendation": true,
      "is_placeholder": false,
      "raw_markdown_risk": false,
      "broken_equation_risk": false,
      "duplicate_example_risk": false,
      "premium_gated": true,
      "action": "retain"
    },
    {
      "academy": "math",
      "unit": "Geometry & Trigonometry",
      "lesson_id": "area-volume",
      "title": "Area Volume",
      "route": "/sat-math-academy/lesson/area-volume",
      "has_objective": true,
      "has_teaching": true,
      "has_worked_examples": true,
      "has_common_mistakes": true,
      "has_strategy": true,
      "has_knowledge_check": true,
      "has_practice": true,
      "has_mastery_score": true,
      "has_recommendation": true,
      "is_placeholder": false,
      "raw_markdown_risk": false,
      "broken_equation_risk": false,
      "duplicate_example_risk": false,
      "premium_gated": true,
      "action": "retain"
    },
    {
      "academy": "math",
      "unit": "Geometry & Trigonometry",
      "lesson_id": "lines-angles-triangles",
      "title": "Lines Angles Triangles",
      "route": "/sat-math-academy/lesson/lines-angles-triangles",
      "has_objective": true,
      "has_teaching": true,
      "has_worked_examples": true,
      "has_common_mistakes": true,
      "has_strategy": true,
      "has_knowledge_check": true,
      "has_practice": true,
      "has_mastery_score": true,
      "has_recommendation": true,
      "is_placeholder": false,
      "raw_markdown_risk": false,
      "broken_equation_risk": false,
      "duplicate_example_risk": false,
      "premium_gated": true,
      "action": "retain"
    },
    {
      "academy": "math",
      "unit": "Geometry & Trigonometry",
      "lesson_id": "right-triangles-trig",
      "title": "Right Triangles Trig",
      "route": "/sat-math-academy/lesson/right-triangles-trig",
      "has_objective": true,
      "has_teaching": true,
      "has_worked_examples": true,
      "has_common_mistakes": true,
      "has_strategy": true,
      "has_knowledge_check": true,
      "has_practice": true,
      "has_mastery_score": true,
      "has_recommendation": true,
      "is_placeholder": false,
      "raw_markdown_risk": false,
      "broken_equation_risk": false,
      "duplicate_example_risk": false,
      "premium_gated": true,
      "action": "retain"
    },
    {
      "academy": "math",
      "unit": "Geometry & Trigonometry",
      "lesson_id": "circles",
      "title": "Circles",
      "route": "/sat-math-academy/lesson/circles",
      "has_objective": true,
      "has_teaching": true,
      "has_worked_examples": true,
      "has_common_mistakes": true,
      "has_strategy": true,
      "has_knowledge_check": true,
      "has_practice": true,
      "has_mastery_score": true,
      "has_recommendation": true,
      "is_placeholder": false,
      "raw_markdown_risk": false,
      "broken_equation_risk": false,
      "duplicate_example_risk": false,
      "premium_gated": true,
      "action": "retain"
    }
  ]
}